email_function_failure_traceback/__init__.py
email_function_failure_traceback-0.0.2.dist-info/METADATA
email_function_failure_traceback-0.0.2.dist-info/WHEEL
email_function_failure_traceback-0.0.2.dist-info/top_level.txt
email_function_failure_traceback-0.0.2.dist-info/RECORD
