Metadata-Version: 2.1
Name: email-function-failure-traceback
Version: 0.0.2
Summary: Failed Function Error Traceback Email.
Home-page: https://github.com/sarenehan/email_function_failure_traceback
Author: Stewart Renehan
Author-email: sarenehan@gmail.com
License: UNKNOWN
Platform: UNKNOWN
Classifier: Programming Language :: Python :: 3
Classifier: License :: OSI Approved :: MIT License
Classifier: Operating System :: OS Independent
